mfrc522/MFRC522.py
mfrc522/SimpleMFRC522.py
mfrc522/__init__.py
mfrc522-0.0.6.dist-info/LICENSE
mfrc522-0.0.6.dist-info/METADATA
mfrc522-0.0.6.dist-info/WHEEL
mfrc522-0.0.6.dist-info/top_level.txt
mfrc522-0.0.6.dist-info/RECORD
