Metadata-Version: 2.1
Name: mfrc522
Version: 0.0.6
Summary: A library to integrate the MFRC522 RFID readers with the Raspberry Pi
Home-page: https://github.com/pimylifeup/MFRC522-python
Author: Pi My Life Up
Author-email: support@pimylifeup.com
License: UNKNOWN
Platform: UNKNOWN
Classifier: Programming Language :: Python :: 2.7
Classifier: Programming Language :: Python :: 3
Classifier: License :: OSI Approved :: GNU General Public License v3 (GPLv3)
Classifier: Operating System :: POSIX :: Linux
Classifier: Topic :: System :: Hardware
Requires-Dist: RPi.GPIO
Requires-Dist: spidev
